odoo/addons/stock_picking_move_package_to_package/README.rst
odoo/addons/stock_picking_move_package_to_package/__init__.py
odoo/addons/stock_picking_move_package_to_package/__manifest__.py
odoo/addons/stock_picking_move_package_to_package/i18n/it.po
odoo/addons/stock_picking_move_package_to_package/i18n/stock_picking_move_package_to_package.pot
odoo/addons/stock_picking_move_package_to_package/models/__init__.py
odoo/addons/stock_picking_move_package_to_package/models/stock_package_level.py
odoo/addons/stock_picking_move_package_to_package/readme/CONFIGURE.md
odoo/addons/stock_picking_move_package_to_package/readme/CONTEXT.md
odoo/addons/stock_picking_move_package_to_package/readme/CONTRIBUTORS.md
odoo/addons/stock_picking_move_package_to_package/readme/DESCRIPTION.md
odoo/addons/stock_picking_move_package_to_package/readme/USAGE.md
odoo/addons/stock_picking_move_package_to_package/static/description/icon.png
odoo/addons/stock_picking_move_package_to_package/static/description/icon.svg
odoo/addons/stock_picking_move_package_to_package/static/description/index.html
odoo/addons/stock_picking_move_package_to_package/static/img/picking_destination_package.png
odoo/addons/stock_picking_move_package_to_package/tests/__init__.py
odoo/addons/stock_picking_move_package_to_package/tests/test_move_package_to_package.py
odoo/addons/stock_picking_move_package_to_package/views/stock_package_level_view.xml
odoo_addon_stock_picking_move_package_to_package-16.0.1.0.1.2.dist-info/METADATA
odoo_addon_stock_picking_move_package_to_package-16.0.1.0.1.2.dist-info/WHEEL
odoo_addon_stock_picking_move_package_to_package-16.0.1.0.1.2.dist-info/top_level.txt
odoo_addon_stock_picking_move_package_to_package-16.0.1.0.1.2.dist-info/RECORD
